ShuaizhangHeTaDePengyouMenDiyiqiJinghuaDianzishu/README.md
ShuaizhangHeTaDePengyouMenDiyiqiJinghuaDianzishu/__init__.py
ShuaizhangHeTaDePengyouMenDiyiqiJinghuaDianzishu/__main__.py
ShuaizhangHeTaDePengyouMenDiyiqiJinghuaDianzishu/file.pdf
ShuaizhangHeTaDePengyouMenDiyiqiJinghuaDianzishu/index.html
shuaizhang_he_ta_de_pengyou_men_diyiqi_jinghua_dianzishu-2024.3.5.0.dist-info/METADATA
shuaizhang_he_ta_de_pengyou_men_diyiqi_jinghua_dianzishu-2024.3.5.0.dist-info/WHEEL
shuaizhang_he_ta_de_pengyou_men_diyiqi_jinghua_dianzishu-2024.3.5.0.dist-info/entry_points.txt
shuaizhang_he_ta_de_pengyou_men_diyiqi_jinghua_dianzishu-2024.3.5.0.dist-info/top_level.txt
shuaizhang_he_ta_de_pengyou_men_diyiqi_jinghua_dianzishu-2024.3.5.0.dist-info/RECORD
